WGF/__init__.py
WGF/base.py
WGF/common.py
WGF/loader.py
WGF/nodes.py
WGF/tasks.py
WGF/ext/__init__.py
WGF/ext/mapgen.py
WGF-0.1.1.dist-info/LICENSE
WGF-0.1.1.dist-info/METADATA
WGF-0.1.1.dist-info/WHEEL
WGF-0.1.1.dist-info/top_level.txt
WGF-0.1.1.dist-info/RECORD
