Metadata-Version: 2.1
Name: WGF
Version: 0.1.1
Summary: WGF - Whatever Game Framework
Home-page: https://github.com/moonburnt/WGF
Author: moonburnt
Author-email: moonburnt@disroot.org
License: MIT
Platform: UNKNOWN
Classifier: Programming Language :: Python :: 3
Classifier: Development Status :: 5 - Production/Stable
License-File: LICENSE
Requires-Dist: pygame (==2.1.2)
Provides-Extra: toml_support
Requires-Dist: toml (==0.10.2) ; extra == 'toml_support'
